<?xml version="1.0"?>
<?xml-stylesheet type="text/xsl" href="configuration.xsl"?>

<configuration>

<property>
  <name>mapred.job.tracker</name>
  <value>beaker-2:29999</value>
</property>

<property>
  <name>mapred.local.dir</name>
  <value>${hadoop.tmp.dir}/mapred/local</value>
</property>

<property>
  <name>mapred.system.dir</name>
  <value>/mapred/system</value>
</property>

<property>
  <name>mapred.temp.dir</name>
  <value>/mapred/temp</value>
</property>

<property>
  <name>mapred.map.child.java.opts</name>
  <value>-Xmx2048M</value>
</property>

<property>
  <name>mapred.reduce.child.java.opts</name>
  <value>-Xmx2048M</value>
</property>

<property>
  <name>mapred.tasktracker.map.tasks.maximum</name>
  <value>1</value>
</property>

<property>
  <name>mapred.tasktracker.reduce.tasks.maximum</name>
  <value>1</value>
</property>

<property>
  <name>mapred.hosts.exclude</name>
  <value>conf/mapred-bad</value>
</property>

<property>
  <name>mapred.output.compress</name>
  <value>true</value>
</property>

<property>
  <name>mapred.compress.map.output</name>
  <value>true</value>
</property>

<property>
  <name>mapred.output.compression.type</name>
  <value>BLOCK</value>
</property>

<property>
  <name>mapred.output.compression.codec</name>
  <value>org.apache.hadoop.io.compress.GzipCodec</value>
</property>

<property>
  <name>mapred.map.output.compression.codec</name>
  <value>org.apache.hadoop.io.compress.GzipCodec</value>
</property>

<property>
  <name>mapreduce.job.counters.limit</name>
  <value>10000</value>
</property>


</configuration>
